ghot/auth.py
ghot/config.py
ghot/csv_loader.py
ghot/ghot.py
ghot/org_manager.py
ghot/pattern_formatter.py
ghot/user.py
ghot-0.2.0.dist-info/METADATA
ghot-0.2.0.dist-info/WHEEL
ghot-0.2.0.dist-info/entry_points.txt
ghot-0.2.0.dist-info/RECORD
