Metadata-Version: 2.4
Name: ghot
Version: 0.2.0
Summary: GitHub Organization Tools
Project-URL: Documentation, https://joapuiib.github.io/github-organization-tools
Project-URL: Download, https://github.com/joapuiib/github-organization-tools/releases
Project-URL: Homepage, https://joapuiib.github.io/github-organization-tools
Project-URL: Source, https://github.com/joapuiib/github-organization-tools
Project-URL: Tracker, https://github.com/joapuiib/github-organization-tools/issues
Author-email: Joan Puigcerver <joapuiib@gmail.com>
License-Expression: MIT
Classifier: Topic :: Software Development :: Libraries :: Python Modules
Requires-Python: >=3.8
Requires-Dist: colorama
Requires-Dist: gitpython
Requires-Dist: keyring
Requires-Dist: pygithub
